thindf.py
thindf-0.2.5.dist-info/METADATA
thindf-0.2.5.dist-info/RECORD
thindf-0.2.5.dist-info/WHEEL
thindf-0.2.5.dist-info/top_level.txt
